mockredis/__init__.py
mockredis/client.py
mockredis/clock.py
mockredis/exceptions.py
mockredis/lock.py
mockredis/noseplugin.py
mockredis/pipeline.py
mockredis/script.py
mockredis/sortedset.py
mockredispy_kblin-2.9.3.4.dist-info/LICENSE
mockredispy_kblin-2.9.3.4.dist-info/METADATA
mockredispy_kblin-2.9.3.4.dist-info/WHEEL
mockredispy_kblin-2.9.3.4.dist-info/entry_points.txt
mockredispy_kblin-2.9.3.4.dist-info/top_level.txt
mockredispy_kblin-2.9.3.4.dist-info/RECORD
