Metadata-Version: 2.1
Name: mockredispy-kblin
Version: 2.9.3.4
Summary: Mock for redis-py, fork until upstream releases new version
Home-page: http://www.github.com/locationlabs/mockredis
License: Apache2
Platform: UNKNOWN
Provides-Extra: lua
Requires-Dist: lunatic-python-bugfix (==1.1.1) ; extra == 'lua'
